asn1cpython_support/__init__.py
asn1cpython_support/__main__.py
asn1cpython_support/cmake/asn1c-bindings-config.cmake
asn1cpython_support/cmake/modules/asn1c-common.cmake
asn1cpython_support/cmake/modules/asn1c-extension.cmake
asn1cpython_support/cmake/modules/asn1c-utils.cmake
asn1cpython_support-0.0.1.dist-info/METADATA
asn1cpython_support-0.0.1.dist-info/WHEEL
asn1cpython_support-0.0.1.dist-info/RECORD
