Metadata-Version: 2.4
Name: asn1cpython-support
Version: 0.0.1
Summary: CMake support files for ASN.1 C extension bindings
Project-URL: documentation, https://matrixeditor.github.io/asn1c-bindings/
Project-URL: project, https://github.com/MatrixEditor/asn1c-bindings
Author: MatrixEdior
Keywords: asn1,asn1c,pyasn1
